[
    {
        "id":1,
        "name":"Casio Watch",
        "title":"",
        "price":1000,
        "category":"For Sale",
        "image":"/Casio_MRW.jpg",
        "description":"The Casio MRW-200HC-2BVDF is a sporty, durable watch with quartz movement, 100m water resistance, and a resin strap."
    },
    {
        "id":2,
        "name":"Casio Watch",
        "title":"",
        "price":1000,
        "category":"For Sale",
        "image":"/Casio_MRW.jpg",
        "description":"The Casio MRW-200HC-2BVDF is a sporty, durable watch with quartz movement, 100m water resistance, and a resin strap."
    },
    {
        "id":3,
        "name":"Casio Watch",
        "title":"",
        "price":1000,
        "category":"For Sale",
        "image":"/Casio_MRW.jpg",
        "description":"The Casio MRW-200HC-2BVDF is a sporty, durable watch with quartz movement, 100m water resistance, and a resin strap."
    },
    
    





    {
        "id":10,
        "name":"codechef",
        "title":"no image awailable",
        "price":0,
        "category":"Asgn1",
        "image":"",
        "description":"Boost skills with real-world experience through top internships."
    },
    {
        "id":11,
        "name":"Phonepay",
        "title":"no image awailable",
        "price":0,
        "category":"Asgn1",
        "image":"",
        "description":"Boost skills with real-world experience through top internships."
    },
    {
        "id":12,
        "name":"codechef",
        "title":"no image awailable",
        "price":0,
        "category":"Asgn1",
        "image":"",
        "description":"Boost skills with real-world experience through top internships."
    },
    {
        "id":13,
        "name":"hackerrank",
        "title":"no image awailable",
        "price":0,
        "category":"Asgn1",
        "image":"",
        "description":"Boost skills with real-world experience through top internships."
    },

    {
        "id":14,
        "name":"codeforces",
        "title":"no image awailable",
        "price":0,
        "category":"Notes2",
        "image":"/Casio_MRW.jpg",
        "description":"Boost skills with real-world experience through top internships."
    },
    {
        "id":15,
        "name":"hackerrank",
        "title":"no image awailable",
        "price":1000,
        "category":"Notes2",
        "image":"/Casio_MRW.jpg",
        "description":"Boost skills with real-world experience through top internships."
    }
    
]